{
    "usul": [
        {
            "attribute_key": "yuruksemai", 
            "mb_attribute": "Y\u00fcr\u00fcksemai", 
            "source": "http://musicbrainz.org/work/9daf4031-a5ae-4b2b-8fe8-eb7d622cfe61"
        }, 
        {
            "attribute_key": "yuruksemai", 
            "mb_tag": "y\u00fcr\u00fcksemai", 
            "source": "http://musicbrainz.org/recording/46f69bbc-83d8-4d7d-beca-24ecad99a2ec"
        }
    ], 
    "form": [
        {
            "attribute_key": "yuruksemai", 
            "mb_attribute": "Y\u00fcr\u00fcksemai", 
            "source": "http://musicbrainz.org/work/9daf4031-a5ae-4b2b-8fe8-eb7d622cfe61"
        }, 
        {
            "attribute_key": "yuruksemai", 
            "mb_tag": "y\u00fcr\u00fcksemai", 
            "source": "http://musicbrainz.org/recording/46f69bbc-83d8-4d7d-beca-24ecad99a2ec"
        }
    ], 
    "releases": [
        {
            "mbid": "189bbe93-186a-46b8-a6da-df8864e6dd4a", 
            "title": "Bekir S\u0131dk\u0131 Sezgin 14"
        }
    ], 
    "title": "Ab \u00fc Tab ile Bu \u015eeb Haneme Canan Geliyor", 
    "url": "http://musicbrainz.org/recording/46f69bbc-83d8-4d7d-beca-24ecad99a2ec", 
    "artist_credits": [
        {
            "mbid": "7ef61959-65f2-41ab-9ae2-ba890812b7b4", 
            "name": "Bekir S\u0131dk\u0131 Sezgin"
        }
    ], 
    "mbid": "46f69bbc-83d8-4d7d-beca-24ecad99a2ec", 
    "makam": [
        {
            "attribute_key": "suzidilara", 
            "mb_attribute": "Suzidilara", 
            "source": "http://musicbrainz.org/work/9daf4031-a5ae-4b2b-8fe8-eb7d622cfe61"
        }, 
        {
            "attribute_key": "suzidilara", 
            "mb_tag": "suzidilara", 
            "source": "http://musicbrainz.org/recording/46f69bbc-83d8-4d7d-beca-24ecad99a2ec"
        }
    ], 
    "artists": [
        {
            "mbid": "125ec42a-7229-4250-afc5-e057484327fe", 
            "type": "performing orchestra", 
            "name": "[unknown]"
        }, 
        {
            "mbid": "7ef61959-65f2-41ab-9ae2-ba890812b7b4", 
            "type": "vocal", 
            "name": "Bekir S\u0131dk\u0131 Sezgin"
        }
    ], 
    "instrumentation_voicing": "Solo vocal with accompaniment", 
    "works": [
        {
            "mbid": "9daf4031-a5ae-4b2b-8fe8-eb7d622cfe61", 
            "title": "Ab \u00fc Tabiyle Bu \u015eeb Haneme Canan Geliyor"
        }
    ]
}