{
    "usul": [
        {
            "attribute_key": "devrikebir", 
            "mb_attribute": "Devr-i Kebir", 
            "source": "http://musicbrainz.org/work/1d7aa01a-8bf2-43e1-b972-714699db563d"
        }, 
        {
            "attribute_key": "devrikebir", 
            "mb_tag": "devr-i kebir", 
            "source": "http://musicbrainz.org/recording/58ded44d-41cf-432b-be16-7d2ab431f49e"
        }
    ], 
    "form": [
        {
            "attribute_key": "pesrev", 
            "mb_attribute": "Pe\u015frev", 
            "source": "http://musicbrainz.org/work/1d7aa01a-8bf2-43e1-b972-714699db563d"
        }, 
        {
            "attribute_key": "pesrev", 
            "mb_tag": "pe\u015frev", 
            "source": "http://musicbrainz.org/recording/58ded44d-41cf-432b-be16-7d2ab431f49e"
        }
    ], 
    "releases": [
        {
            "mbid": "b8768e6d-65ed-4d26-9b47-51793c24b5a0", 
            "title": "T\u00fcrk Sanat M\u00fczi\u011fi Besteleri Saz Eserleri 1"
        }, 
        {
            "mbid": "c58f2002-8862-4efb-953b-7324bb7f3e31", 
            "title": "T\u00fcrk Sanat M\u00fczi\u011fi Besteleri Saz Eserleri 3"
        }
    ], 
    "title": "Pe\u015frev", 
    "url": "http://musicbrainz.org/recording/58ded44d-41cf-432b-be16-7d2ab431f49e", 
    "artist_credits": [
        {
            "mbid": "ef074ab6-a2a8-42f7-a454-068265023697", 
            "name": "Aziz T\u00fcrk Sanat M\u00fczi\u011fi Grubu"
        }
    ], 
    "mbid": "58ded44d-41cf-432b-be16-7d2ab431f49e", 
    "makam": [
        {
            "attribute_key": "nihavent", 
            "mb_attribute": "Nihavent", 
            "source": "http://musicbrainz.org/work/1d7aa01a-8bf2-43e1-b972-714699db563d"
        }, 
        {
            "attribute_key": "nihavent", 
            "mb_tag": "nihavent", 
            "source": "http://musicbrainz.org/recording/58ded44d-41cf-432b-be16-7d2ab431f49e"
        }
    ], 
    "artists": [
        {
            "mbid": "ef074ab6-a2a8-42f7-a454-068265023697", 
            "type": "performing orchestra", 
            "name": "Aziz T\u00fcrk Sanat M\u00fczi\u011fi Grubu"
        }
    ], 
    "instrumentation_voicing": "Ensemble instrumental", 
    "works": [
        {
            "mbid": "1d7aa01a-8bf2-43e1-b972-714699db563d", 
            "title": "Nihavend Pe\u015frev"
        }
    ]
}