{
    "instrumentation_voicing": "Solo instrumental", 
    "form": [
        {
            "attribute_key": "taksim", 
            "mb_tag": "taksim", 
            "source": "http://musicbrainz.org/recording/6f142c0a-de95-467c-8231-1444d6797c03"
        }
    ], 
    "releases": [
        {
            "mbid": "291a62d1-907b-41b0-8f38-44666de278dc", 
            "title": "14 Makamda Keman Taksimleri"
        }
    ], 
    "title": "Hicazkar Taksimi", 
    "url": "http://musicbrainz.org/recording/6f142c0a-de95-467c-8231-1444d6797c03", 
    "artist_credits": [
        {
            "mbid": "125ec42a-7229-4250-afc5-e057484327fe", 
            "name": "[unknown]"
        }
    ], 
    "mbid": "6f142c0a-de95-467c-8231-1444d6797c03", 
    "makam": [
        {
            "attribute_key": "hicazkar", 
            "mb_tag": "hicazkar", 
            "source": "http://musicbrainz.org/recording/6f142c0a-de95-467c-8231-1444d6797c03"
        }
    ], 
    "artists": [
        {
            "mbid": "125ec42a-7229-4250-afc5-e057484327fe", 
            "attribute-list": [
                "violin"
            ], 
            "type": "instrument", 
            "name": "[unknown]"
        }
    ], 
    "usul": [
        {
            "attribute_key": "serbest", 
            "mb_tag": "serbest", 
            "source": "http://musicbrainz.org/recording/6f142c0a-de95-467c-8231-1444d6797c03"
        }
    ]
}